alphabt_new/__init__.py
alphabt_new/config.py
alphabt_new/data_utils.py
alphabt_new/engine.py
alphabt_new/lib.py
alphabt_new/object.py
alphabt_new/performance.py
QDNB-0.0.9.dist-info/METADATA
QDNB-0.0.9.dist-info/WHEEL
QDNB-0.0.9.dist-info/top_level.txt
QDNB-0.0.9.dist-info/RECORD
