Metadata-Version: 2.1
Name: QDNB
Version: 0.0.9
Summary: bt api
Home-page: https://oa.csc.com.cn
Author: wangcc
Author-email: 705190651@qq.com
License: UNKNOWN
Platform: UNKNOWN
